android_utils.py
base_plugin.py
client_utils.py
dev_server.py
file_utils.py
hook_utils.py
markdown_utils.py
plugin_settings.py
exteragram_utils/__init__.py
exteragram_utils/dev_client.py
ui/__init__.py
ui/alert.py
ui/bulletin.py
ui/settings.py
utils/__init__.py
utils/metadata_parser.py
exteragram_utils-0.1.2.dist-info/METADATA
exteragram_utils-0.1.2.dist-info/WHEEL
exteragram_utils-0.1.2.dist-info/entry_points.txt
exteragram_utils-0.1.2.dist-info/top_level.txt
exteragram_utils-0.1.2.dist-info/RECORD
