Metadata-Version: 2.4
Name: exteragram-utils
Version: 0.1.2
Summary: Development utilities for exteraGram plugins
Requires-Python: >=3.8
Requires-Dist: watchdog>=3.0.0
Requires-Dist: aiofiles>=23.0.0
Requires-Dist: black>=24.8.0
Requires-Dist: beautifulsoup4>=4.13.4
Requires-Dist: lxml>=6.0.0
Requires-Dist: pillow>=10.4.0
Requires-Dist: requests>=2.32.4
Requires-Dist: pyyaml>=6.0.3
